cybersource_hosted_checkout/__init__.py
cybersource_hosted_checkout/models.py
cybersource_hosted_checkout/utils.py
cybersource_hosted_checkout/templates/cybersource_hosted_checkout/post_to_cybersource.html
cybersource_hosted_checkout/tests/__init__.py
cybersource_hosted_checkout/tests/test_utils.py
django_cybersource_hosted_checkout-0.0.6.dist-info/METADATA
django_cybersource_hosted_checkout-0.0.6.dist-info/RECORD
django_cybersource_hosted_checkout-0.0.6.dist-info/WHEEL
django_cybersource_hosted_checkout-0.0.6.dist-info/top_level.txt
