Metadata-Version: 2.1
Name: django-cybersource-hosted-checkout
Version: 0.0.6
Summary: This package provides utilities for using CyberSource Secure Acceptance Hosted Checkout.
Home-page: https://github.com/wharton/django-cybersource-hosted-checkout
Author: Tim Allen
Author-email: tallen@wharton.upenn.edu
License: UNKNOWN
Platform: UNKNOWN
Classifier: Development Status :: 3 - Alpha
Classifier: Environment :: Web Environment
Classifier: Intended Audience :: Developers
Classifier: License :: OSI Approved :: BSD License
Classifier: Operating System :: OS Independent
Classifier: Programming Language :: Python :: 3
Classifier: Programming Language :: Python :: 3.5
Classifier: Programming Language :: Python :: 3.6
Classifier: Framework :: Django
Classifier: Topic :: Internet :: WWW/HTTP
Classifier: Topic :: Internet :: WWW/HTTP :: Dynamic Content
Requires-Dist: Django
